hellonjue/__init__.py
hellonjue/functions.py
tests/__init__.py
tests/test_functions.py
hellonjue-0.1.0.dist-info/METADATA
hellonjue-0.1.0.dist-info/WHEEL
hellonjue-0.1.0.dist-info/top_level.txt
hellonjue-0.1.0.dist-info/RECORD
