Metadata-Version: 2.1
Name: hellonjue
Version: 0.1.0
Summary: My first Python library for ASCII art generation
Home-page: UNKNOWN
Author: Njue Lewis
Author-email: your_email@example.com
License: MIT
Platform: UNKNOWN
Classifier: Development Status :: 3 - Alpha
Classifier: Intended Audience :: Developers
Classifier: Programming Language :: Python :: 3
Classifier: License :: OSI Approved :: MIT License
Classifier: Operating System :: OS Independent
Requires-Python: >=3.6
